{
  "workflow_key": "session_20251107_104633::workflow_0",
  "session_id": "session_20251107_104633",
  "workflow_id": "workflow_0",
  "workflow_type": "interaction",
  "description": "Click/interact → Click/interact → Click/interact → Click/interact → ... and 45 more actions",
  "goal": "Executing automation scripts",
  "confidence": 0.7,
  "timestamp": "2025-11-08T10:02:03.577318",
  "summary": [
    "Workflow captured from session session_20251107_104633 (interaction).",
    "Contains 50 recorded actions with goal: Executing automation scripts.",
    "Top intents detected:",
    "  • Automation Control (50 steps)",
    "Primary applications involved:",
    "  • python.exe (50 steps)",
    "Common screens/pages:",
    "  • Dashboard (39 steps)",
    "  • Monitoring Started (11 steps)",
    "Suggested interpretation:",
    "  This appears to be a session controlling automation tools (launching bots, monitoring)."
  ],
  "steps": [
    {
      "step_number": 1,
      "action_id": "mouse_2025-11-07T10:46:34.300889",
      "intent_category": "automation_control",
      "intent_description": "Controlling automation scripts",
      "intent_confidence": 0.8,
      "contexts": {
        "application": "python.exe",
        "page": "Monitoring Started",
        "state": "interacting"
      },
      "source_session": "session_20251107_104633"
    },
    {
      "step_number": 2,
      "action_id": "mouse_2025-11-07T10:46:34.302080",
      "intent_category": "automation_control",
      "intent_description": "Controlling automation scripts",
      "intent_confidence": 0.8,
      "contexts": {
        "application": "python.exe",
        "page": "Monitoring Started",
        "state": "interacting"
      },
      "source_session": "session_20251107_104633"
    },
    {
      "step_number": 3,
      "action_id": "screen_2025-11-07T10:46:34.427666",
      "intent_category": "automation_control",
      "intent_description": "Controlling automation scripts",
      "intent_confidence": 0.8,
      "contexts": {
        "application": "python.exe",
        "page": "Monitoring Started",
        "state": "viewing"
      },
      "source_session": "session_20251107_104633"
    },
    {
      "step_number": 4,
      "action_id": "mouse_2025-11-07T10:46:34.430545",
      "intent_category": "automation_control",
      "intent_description": "Controlling automation scripts",
      "intent_confidence": 0.8,
      "contexts": {
        "application": "python.exe",
        "page": "Monitoring Started",
        "state": "interacting"
      },
      "source_session": "session_20251107_104633"
    },
    {
      "step_number": 5,
      "action_id": "mouse_2025-11-07T10:46:34.772819",
      "intent_category": "automation_control",
      "intent_description": "Controlling automation scripts",
      "intent_confidence": 0.8,
      "contexts": {
        "application": "python.exe",
        "page": "Monitoring Started",
        "state": "interacting"
      },
      "source_session": "session_20251107_104633"
    },
    {
      "step_number": 6,
      "action_id": "mouse_2025-11-07T10:46:34.773875",
      "intent_category": "automation_control",
      "intent_description": "Controlling automation scripts",
      "intent_confidence": 0.8,
      "contexts": {
        "application": "python.exe",
        "page": "Monitoring Started",
        "state": "interacting"
      },
      "source_session": "session_20251107_104633"
    },
    {
      "step_number": 7,
      "action_id": "mouse_2025-11-07T10:46:34.852870",
      "intent_category": "automation_control",
      "intent_description": "Controlling automation scripts",
      "intent_confidence": 0.8,
      "contexts": {
        "application": "python.exe",
        "page": "Monitoring Started",
        "state": "interacting"
      },
      "source_session": "session_20251107_104633"
    },
    {
      "step_number": 8,
      "action_id": "mouse_2025-11-07T10:46:35.228734",
      "intent_category": "automation_control",
      "intent_description": "Controlling automation scripts",
      "intent_confidence": 0.8,
      "contexts": {
        "application": "python.exe",
        "page": "Monitoring Started",
        "state": "interacting"
      },
      "source_session": "session_20251107_104633"
    },
    {
      "step_number": 9,
      "action_id": "mouse_2025-11-07T10:46:35.229552",
      "intent_category": "automation_control",
      "intent_description": "Controlling automation scripts",
      "intent_confidence": 0.8,
      "contexts": {
        "application": "python.exe",
        "page": "Monitoring Started",
        "state": "interacting"
      },
      "source_session": "session_20251107_104633"
    },
    {
      "step_number": 10,
      "action_id": "screen_2025-11-07T10:46:35.318535",
      "intent_category": "automation_control",
      "intent_description": "Controlling automation scripts",
      "intent_confidence": 0.8,
      "contexts": {
        "application": "python.exe",
        "page": "Monitoring Started",
        "state": "viewing"
      },
      "source_session": "session_20251107_104633"
    },
    {
      "step_number": 11,
      "action_id": "mouse_2025-11-07T10:46:35.320904",
      "intent_category": "automation_control",
      "intent_description": "Controlling automation scripts",
      "intent_confidence": 0.8,
      "contexts": {
        "application": "python.exe",
        "page": "Monitoring Started",
        "state": "interacting"
      },
      "source_session": "session_20251107_104633"
    },
    {
      "step_number": 12,
      "action_id": "screen_2025-11-07T10:46:36.379901",
      "intent_category": "automation_control",
      "intent_description": "Controlling automation scripts",
      "intent_confidence": 0.8,
      "contexts": {
        "application": "python.exe",
        "page": "Dashboard",
        "state": "viewing",
        "task": "Automation Oversight"
      },
      "source_session": "session_20251107_104633"
    },
    {
      "step_number": 13,
      "action_id": "mouse_2025-11-07T10:46:36.382618",
      "intent_category": "automation_control",
      "intent_description": "Controlling automation scripts",
      "intent_confidence": 0.8,
      "contexts": {
        "application": "python.exe",
        "page": "Dashboard",
        "state": "interacting",
        "task": "Automation Oversight"
      },
      "source_session": "session_20251107_104633"
    },
    {
      "step_number": 14,
      "action_id": "mouse_2025-11-07T10:46:36.383043",
      "intent_category": "automation_control",
      "intent_description": "Controlling automation scripts",
      "intent_confidence": 0.8,
      "contexts": {
        "application": "python.exe",
        "page": "Dashboard",
        "state": "interacting",
        "task": "Automation Oversight"
      },
      "source_session": "session_20251107_104633"
    },
    {
      "step_number": 15,
      "action_id": "mouse_2025-11-07T10:46:36.413508",
      "intent_category": "automation_control",
      "intent_description": "Controlling automation scripts",
      "intent_confidence": 0.8,
      "contexts": {
        "application": "python.exe",
        "page": "Dashboard",
        "state": "interacting",
        "task": "Automation Oversight"
      },
      "source_session": "session_20251107_104633"
    },
    {
      "step_number": 16,
      "action_id": "mouse_2025-11-07T10:46:36.668466",
      "intent_category": "automation_control",
      "intent_description": "Controlling automation scripts",
      "intent_confidence": 0.8,
      "contexts": {
        "application": "python.exe",
        "page": "Dashboard",
        "state": "interacting",
        "task": "Automation Oversight"
      },
      "source_session": "session_20251107_104633"
    },
    {
      "step_number": 17,
      "action_id": "mouse_2025-11-07T10:46:36.668984",
      "intent_category": "automation_control",
      "intent_description": "Controlling automation scripts",
      "intent_confidence": 0.8,
      "contexts": {
        "application": "python.exe",
        "page": "Dashboard",
        "state": "interacting",
        "task": "Automation Oversight"
      },
      "source_session": "session_20251107_104633"
    },
    {
      "step_number": 18,
      "action_id": "screen_2025-11-07T10:46:37.455343",
      "intent_category": "automation_control",
      "intent_description": "Controlling automation scripts",
      "intent_confidence": 0.8,
      "contexts": {
        "application": "python.exe",
        "page": "Dashboard",
        "state": "viewing",
        "task": "Automation Oversight"
      },
      "source_session": "session_20251107_104633"
    },
    {
      "step_number": 19,
      "action_id": "screen_2025-11-07T10:46:38.526361",
      "intent_category": "automation_control",
      "intent_description": "Controlling automation scripts",
      "intent_confidence": 0.8,
      "contexts": {
        "application": "python.exe",
        "page": "Dashboard",
        "state": "viewing",
        "task": "Automation Oversight"
      },
      "source_session": "session_20251107_104633"
    },
    {
      "step_number": 20,
      "action_id": "mouse_2025-11-07T10:46:39.372958",
      "intent_category": "automation_control",
      "intent_description": "Controlling automation scripts",
      "intent_confidence": 0.8,
      "contexts": {
        "application": "python.exe",
        "page": "Dashboard",
        "state": "interacting",
        "task": "Automation Oversight"
      },
      "source_session": "session_20251107_104633"
    },
    {
      "step_number": 21,
      "action_id": "mouse_2025-11-07T10:46:39.374095",
      "intent_category": "automation_control",
      "intent_description": "Controlling automation scripts",
      "intent_confidence": 0.8,
      "contexts": {
        "application": "python.exe",
        "page": "Dashboard",
        "state": "interacting",
        "task": "Automation Oversight"
      },
      "source_session": "session_20251107_104633"
    },
    {
      "step_number": 22,
      "action_id": "mouse_2025-11-07T10:46:39.468710",
      "intent_category": "automation_control",
      "intent_description": "Controlling automation scripts",
      "intent_confidence": 0.8,
      "contexts": {
        "application": "python.exe",
        "page": "Dashboard",
        "state": "interacting",
        "task": "Automation Oversight"
      },
      "source_session": "session_20251107_104633"
    },
    {
      "step_number": 23,
      "action_id": "screen_2025-11-07T10:46:39.611151",
      "intent_category": "automation_control",
      "intent_description": "Controlling automation scripts",
      "intent_confidence": 0.8,
      "contexts": {
        "application": "python.exe",
        "page": "Dashboard",
        "state": "viewing",
        "task": "Automation Oversight"
      },
      "source_session": "session_20251107_104633"
    },
    {
      "step_number": 24,
      "action_id": "mouse_2025-11-07T10:46:40.116883",
      "intent_category": "automation_control",
      "intent_description": "Controlling automation scripts",
      "intent_confidence": 0.8,
      "contexts": {
        "application": "python.exe",
        "page": "Dashboard",
        "state": "interacting",
        "task": "Automation Oversight"
      },
      "source_session": "session_20251107_104633"
    },
    {
      "step_number": 25,
      "action_id": "mouse_2025-11-07T10:46:40.117847",
      "intent_category": "automation_control",
      "intent_description": "Controlling automation scripts",
      "intent_confidence": 0.8,
      "contexts": {
        "application": "python.exe",
        "page": "Dashboard",
        "state": "interacting",
        "task": "Automation Oversight"
      },
      "source_session": "session_20251107_104633"
    },
    {
      "step_number": 26,
      "action_id": "mouse_2025-11-07T10:46:40.213052",
      "intent_category": "automation_control",
      "intent_description": "Controlling automation scripts",
      "intent_confidence": 0.8,
      "contexts": {
        "application": "python.exe",
        "page": "Dashboard",
        "state": "interacting",
        "task": "Automation Oversight"
      },
      "source_session": "session_20251107_104633"
    },
    {
      "step_number": 27,
      "action_id": "mouse_2025-11-07T10:46:40.532892",
      "intent_category": "automation_control",
      "intent_description": "Controlling automation scripts",
      "intent_confidence": 0.8,
      "contexts": {
        "application": "python.exe",
        "page": "Dashboard",
        "state": "interacting",
        "task": "Automation Oversight"
      },
      "source_session": "session_20251107_104633"
    },
    {
      "step_number": 28,
      "action_id": "mouse_2025-11-07T10:46:40.533776",
      "intent_category": "automation_control",
      "intent_description": "Controlling automation scripts",
      "intent_confidence": 0.8,
      "contexts": {
        "application": "python.exe",
        "page": "Dashboard",
        "state": "interacting",
        "task": "Automation Oversight"
      },
      "source_session": "session_20251107_104633"
    },
    {
      "step_number": 29,
      "action_id": "mouse_2025-11-07T10:46:40.637212",
      "intent_category": "automation_control",
      "intent_description": "Controlling automation scripts",
      "intent_confidence": 0.8,
      "contexts": {
        "application": "python.exe",
        "page": "Dashboard",
        "state": "interacting",
        "task": "Automation Oversight"
      },
      "source_session": "session_20251107_104633"
    },
    {
      "step_number": 30,
      "action_id": "screen_2025-11-07T10:46:40.685902",
      "intent_category": "automation_control",
      "intent_description": "Controlling automation scripts",
      "intent_confidence": 0.8,
      "contexts": {
        "application": "python.exe",
        "page": "Dashboard",
        "state": "viewing",
        "task": "Automation Oversight"
      },
      "source_session": "session_20251107_104633"
    },
    {
      "step_number": 31,
      "action_id": "screen_2025-11-07T10:46:41.789174",
      "intent_category": "automation_control",
      "intent_description": "Controlling automation scripts",
      "intent_confidence": 0.8,
      "contexts": {
        "application": "python.exe",
        "page": "Dashboard",
        "state": "viewing",
        "task": "Automation Oversight"
      },
      "source_session": "session_20251107_104633"
    },
    {
      "step_number": 32,
      "action_id": "screen_2025-11-07T10:46:42.774967",
      "intent_category": "automation_control",
      "intent_description": "Controlling automation scripts",
      "intent_confidence": 0.8,
      "contexts": {
        "application": "python.exe",
        "page": "Dashboard",
        "state": "viewing",
        "task": "Automation Oversight"
      },
      "source_session": "session_20251107_104633"
    },
    {
      "step_number": 33,
      "action_id": "mouse_2025-11-07T10:46:43.620655",
      "intent_category": "automation_control",
      "intent_description": "Controlling automation scripts",
      "intent_confidence": 0.8,
      "contexts": {
        "application": "python.exe",
        "page": "Dashboard",
        "state": "interacting",
        "task": "Automation Oversight"
      },
      "source_session": "session_20251107_104633"
    },
    {
      "step_number": 34,
      "action_id": "mouse_2025-11-07T10:46:43.621425",
      "intent_category": "automation_control",
      "intent_description": "Controlling automation scripts",
      "intent_confidence": 0.8,
      "contexts": {
        "application": "python.exe",
        "page": "Dashboard",
        "state": "interacting",
        "task": "Automation Oversight"
      },
      "source_session": "session_20251107_104633"
    },
    {
      "step_number": 35,
      "action_id": "mouse_2025-11-07T10:46:43.668857",
      "intent_category": "automation_control",
      "intent_description": "Controlling automation scripts",
      "intent_confidence": 0.8,
      "contexts": {
        "application": "python.exe",
        "page": "Dashboard",
        "state": "interacting",
        "task": "Automation Oversight"
      },
      "source_session": "session_20251107_104633"
    },
    {
      "step_number": 36,
      "action_id": "mouse_2025-11-07T10:46:43.716932",
      "intent_category": "automation_control",
      "intent_description": "Controlling automation scripts",
      "intent_confidence": 0.8,
      "contexts": {
        "application": "python.exe",
        "page": "Dashboard",
        "state": "interacting",
        "task": "Automation Oversight"
      },
      "source_session": "session_20251107_104633"
    },
    {
      "step_number": 37,
      "action_id": "mouse_2025-11-07T10:46:43.717467",
      "intent_category": "automation_control",
      "intent_description": "Controlling automation scripts",
      "intent_confidence": 0.8,
      "contexts": {
        "application": "python.exe",
        "page": "Dashboard",
        "state": "interacting",
        "task": "Automation Oversight"
      },
      "source_session": "session_20251107_104633"
    },
    {
      "step_number": 38,
      "action_id": "screen_2025-11-07T10:46:43.846612",
      "intent_category": "automation_control",
      "intent_description": "Controlling automation scripts",
      "intent_confidence": 0.8,
      "contexts": {
        "application": "python.exe",
        "page": "Dashboard",
        "state": "viewing",
        "task": "Automation Oversight"
      },
      "source_session": "session_20251107_104633"
    },
    {
      "step_number": 39,
      "action_id": "screen_2025-11-07T10:46:44.914308",
      "intent_category": "automation_control",
      "intent_description": "Controlling automation scripts",
      "intent_confidence": 0.8,
      "contexts": {
        "application": "python.exe",
        "page": "Dashboard",
        "state": "viewing",
        "task": "Automation Oversight"
      },
      "source_session": "session_20251107_104633"
    },
    {
      "step_number": 40,
      "action_id": "mouse_2025-11-07T10:46:45.116634",
      "intent_category": "automation_control",
      "intent_description": "Controlling automation scripts",
      "intent_confidence": 0.8,
      "contexts": {
        "application": "python.exe",
        "page": "Dashboard",
        "state": "interacting",
        "task": "Automation Oversight"
      },
      "source_session": "session_20251107_104633"
    },
    {
      "step_number": 41,
      "action_id": "mouse_2025-11-07T10:46:45.117175",
      "intent_category": "automation_control",
      "intent_description": "Controlling automation scripts",
      "intent_confidence": 0.8,
      "contexts": {
        "application": "python.exe",
        "page": "Dashboard",
        "state": "interacting",
        "task": "Automation Oversight"
      },
      "source_session": "session_20251107_104633"
    },
    {
      "step_number": 42,
      "action_id": "screen_2025-11-07T10:46:45.990340",
      "intent_category": "automation_control",
      "intent_description": "Controlling automation scripts",
      "intent_confidence": 0.8,
      "contexts": {
        "application": "python.exe",
        "page": "Dashboard",
        "state": "viewing",
        "task": "Automation Oversight"
      },
      "source_session": "session_20251107_104633"
    },
    {
      "step_number": 43,
      "action_id": "screen_2025-11-07T10:46:47.100299",
      "intent_category": "automation_control",
      "intent_description": "Controlling automation scripts",
      "intent_confidence": 0.8,
      "contexts": {
        "application": "python.exe",
        "page": "Dashboard",
        "state": "viewing",
        "task": "Automation Oversight"
      },
      "source_session": "session_20251107_104633"
    },
    {
      "step_number": 44,
      "action_id": "screen_2025-11-07T10:46:48.132693",
      "intent_category": "automation_control",
      "intent_description": "Controlling automation scripts",
      "intent_confidence": 0.8,
      "contexts": {
        "application": "python.exe",
        "page": "Dashboard",
        "state": "viewing",
        "task": "Automation Oversight"
      },
      "source_session": "session_20251107_104633"
    },
    {
      "step_number": 45,
      "action_id": "mouse_2025-11-07T10:46:48.532942",
      "intent_category": "automation_control",
      "intent_description": "Controlling automation scripts",
      "intent_confidence": 0.8,
      "contexts": {
        "application": "python.exe",
        "page": "Dashboard",
        "state": "interacting",
        "task": "Automation Oversight"
      },
      "source_session": "session_20251107_104633"
    },
    {
      "step_number": 46,
      "action_id": "mouse_2025-11-07T10:46:48.533835",
      "intent_category": "automation_control",
      "intent_description": "Controlling automation scripts",
      "intent_confidence": 0.8,
      "contexts": {
        "application": "python.exe",
        "page": "Dashboard",
        "state": "interacting",
        "task": "Automation Oversight"
      },
      "source_session": "session_20251107_104633"
    },
    {
      "step_number": 47,
      "action_id": "screen_2025-11-07T10:46:49.122336",
      "intent_category": "automation_control",
      "intent_description": "Controlling automation scripts",
      "intent_confidence": 0.8,
      "contexts": {
        "application": "python.exe",
        "page": "Dashboard",
        "state": "viewing",
        "task": "Automation Oversight"
      },
      "source_session": "session_20251107_104633"
    },
    {
      "step_number": 48,
      "action_id": "screen_2025-11-07T10:46:50.213747",
      "intent_category": "automation_control",
      "intent_description": "Controlling automation scripts",
      "intent_confidence": 0.8,
      "contexts": {
        "application": "python.exe",
        "page": "Dashboard",
        "state": "viewing",
        "task": "Automation Oversight"
      },
      "source_session": "session_20251107_104633"
    },
    {
      "step_number": 49,
      "action_id": "mouse_2025-11-07T10:46:51.213204",
      "intent_category": "automation_control",
      "intent_description": "Controlling automation scripts",
      "intent_confidence": 0.8,
      "contexts": {
        "application": "python.exe",
        "page": "Dashboard",
        "state": "interacting",
        "task": "Automation Oversight"
      },
      "source_session": "session_20251107_104633"
    },
    {
      "step_number": 50,
      "action_id": "mouse_2025-11-07T10:46:51.214062",
      "intent_category": "automation_control",
      "intent_description": "Controlling automation scripts",
      "intent_confidence": 0.8,
      "contexts": {
        "application": "python.exe",
        "page": "Dashboard",
        "state": "interacting",
        "task": "Automation Oversight"
      },
      "source_session": "session_20251107_104633"
    }
  ]
}